ammar_filter_post/__init__.py
ammar_filter_post/ammar_filter_post.py
ammar_filter_post-1.1.0.dist-info/LICENSE
ammar_filter_post-1.1.0.dist-info/METADATA
ammar_filter_post-1.1.0.dist-info/WHEEL
ammar_filter_post-1.1.0.dist-info/top_level.txt
ammar_filter_post-1.1.0.dist-info/RECORD
