Metadata-Version: 2.1
Name: ammar_filter_post
Version: 1.1.0
Summary: A package to retrieve and sort DynamoDB posts by likes.
Home-page: https://github.com/ammarabrahani@gmail.com/ammar_filter_post
Author: Ammar Abrahani
Author-email: ammarabrahani@gmail.com
Classifier: Programming Language :: Python :: 3
Classifier: License :: OSI Approved :: MIT License
Classifier: Operating System :: OS Independent
Requires-Python: >=3.6
License-File: LICENSE
